MANIFEST.in
README.md
setup.py
bacula_scripts/__init__.py
bacula_scripts/_version.py
bacula_scripts/bacula_add_client.py
bacula_scripts/bacula_db_backup.py
bacula_scripts/bacula_del_catalog_jobids.py
bacula_scripts/bacula_del_failed_jobs_and_volume.py
bacula_scripts/bacula_del_jobs.py
bacula_scripts/bacula_del_media_orphans.py
bacula_scripts/bacula_del_purged_vols.py
bacula_scripts/bacula_del_scatter.py
bacula_scripts/bacula_del_vols_missing_catalog.py
bacula_scripts/bacula_encfs_backup.py
bacula_scripts/bacula_find_backups_bls.py
bacula_scripts/bacula_monitor.py
bacula_scripts/bacula_monitor_dir.py
bacula_scripts/bacula_offsite_backup_age_watch.py
bacula_scripts/bacula_parser.py
bacula_scripts/bacula_prune_all.py
bacula_scripts/bareos-installer-template.ps1
bacula_scripts/bareos-installer.bat
bacula_scripts/disk_full_notifier.py
bacula_scripts/example-bareos-installer.ps1
bacula_scripts/host_uptime_client.py
bacula_scripts/host_uptime_server.py
bacula_scripts.egg-info/PKG-INFO
bacula_scripts.egg-info/SOURCES.txt
bacula_scripts.egg-info/dependency_links.txt
bacula_scripts.egg-info/entry_points.txt
bacula_scripts.egg-info/requires.txt
bacula_scripts.egg-info/top_level.txt
bacula_scripts/__pycache__/bacula_parser.cpython-36.pyc
etc/__init__.py
etc/bacula-scripts/__init__.py
etc/bacula-scripts/bacula_add_client_conf.py
etc/bacula-scripts/bacula_del_catalog_jobids_conf.py
etc/bacula-scripts/bacula_del_jobs_conf.py
etc/bacula-scripts/bacula_del_media_orphans_conf.py
etc/bacula-scripts/bacula_del_purged_vols_conf.py
etc/bacula-scripts/bacula_del_scatter_conf.py
etc/bacula-scripts/bacula_encfs_backup_conf.py
etc/bacula-scripts/bacula_find_backups_bls_conf.py
etc/bacula-scripts/bacula_monitor_conf.py
etc/bacula-scripts/bacula_offsite_backup_age_watch_conf.py
etc/bacula-scripts/disk_full_notifier_conf.py
etc/bacula-scripts/general_conf.py
etc/bacula-scripts/host_uptime_client_conf.py
etc/bacula-scripts/host_uptime_server_conf.py