Metadata-Version: 1.0
Name: bacula-scripts
Version: 1.1.4
Summary: Bunch of bacula scripts. Includes also scripts to realize offsite backup solution.
Home-page: https://github.com/eayin2/bacula_scripts
Author: eayin2
Author-email: eayin2@gmail.com
License: UNKNOWN
Platform: UNKNOWN
